README.txt
setup.py
nnlog/__init__.py
nnlog/nhylog.py
nnlog.egg-info/PKG-INFO
nnlog.egg-info/SOURCES.txt
nnlog.egg-info/dependency_links.txt
nnlog.egg-info/top_level.txt
nnlog.egg-info/zip-safe