Metadata-Version: 1.1
Name: nnlog
Version: 1.0.5
Summary: this is a simple  logging package 
Home-page: http://www.nnzhp.cn/archives/646
Author: HanyangNiu
Author-email: niuhanyang@163.com
License: MIT
Keywords: nnlog python package
